docker_master-0.0.2.dist-info/RECORD
docker_master-0.0.2.dist-info/entry_points.txt
docker_master-0.0.2.dist-info/metadata.json
docker_master-0.0.2.dist-info/METADATA
docker_master-0.0.2.dist-info/DESCRIPTION.rst
docker_master-0.0.2.dist-info/top_level.txt
docker_master-0.0.2.dist-info/WHEEL
dockermaster/__init__.py
dockermaster/main.py
