Metadata-Version: 1.1
Name: docker-master
Version: 0.0.2
Summary: An alternative to docker-compose
Home-page: https://github.com/mbodenhamer/docker-master
Author: Matt Bodenhamer
Author-email: mbodenhamer@mbodenhamer.com
License: MIT
Keywords: docker,application,docker-compose,compose
Platform: UNKNOWN
Classifier: Development Status :: 2 - Pre-Alpha
Classifier: Environment :: Console
Classifier: Intended Audience :: Developers
Classifier: Intended Audience :: System Administrators
Classifier: License :: OSI Approved :: MIT License
Classifier: Operating System :: OS Independent
Classifier: Programming Language :: Python
Classifier: Programming Language :: Python :: 2.7
Classifier: Programming Language :: Python :: 3.4
Classifier: Programming Language :: Python :: 3.5
Classifier: Topic :: Utilities
